urdf2casadi/__init__.py
urdf2casadi/geometry/__init__.py
urdf2casadi/geometry/dual_quaternion.py
urdf2casadi/geometry/plucker.py
urdf2casadi/geometry/quaternion.py
urdf2casadi/geometry/transformation_matrix.py
urdf2casadi/urdfparser.py
urdf2casadi-1.2.0.dist-info/LICENSE
urdf2casadi-1.2.0.dist-info/WHEEL
urdf2casadi-1.2.0.dist-info/METADATA
urdf2casadi-1.2.0.dist-info/RECORD
